Workbook

Sheet Summary
A1: Metric | B1: Value | C1: Interpretation
A2: Security | B2: =Inputs!B2 -> FN FS9548 Mtge | C2: Fannie Mae UMBS 15-year pool, 3.0% pass-through
A3: BVAL bid (clean) | B3: =Inputs!$B$17 -> 97.738281 | C3: 30 Apr 2026
A4: PART I: AGENCY
A5: Model value, clean (10,000 paths) | B5: ='Agency MC Output'!E4 -> 98.197988 | C5: 178 PSA with refinancing overlay; Treasury-calibrated paths
A6: Monte Carlo standard error | B6: ='Agency MC Output'!E5 -> 0.00026981306 | C6: Simulation noise is negligible
A7: Model − market | B7: ='Agency MC Output'!E7 -> 0.45970715 | C7: Positive: above market at zero OAS
A8: OAS at BVAL bid (bp) | B8: 25.669507 | C8: Spread over simulated Treasury short rates that reprices the bid
A9: Bloomberg BAM TOAS (bp) | B9: 17.9 | C9: Bloomberg's own model, for comparison
A10: Effective duration (yrs) | B10: 1.7945153 | C10: ±25 bp parallel curve shift, OAS held constant
A11: Conclusion | B11: Fair to slightly cheap | C11: OAS about 8 bp wider than Bloomberg's TOAS; varies ±10 bp across 100-300 PSA, so not certain
A12: PART II: PRIVATE LABEL (A-rated guarantor)
A13: Annual PD / recovery | B13: 0.10% / 40% | C13: See Credit Risk
A14: Model value, clean | B14: ='Private MC Output'!E4 -> 98.089854 | C14: Expected cash-flow approach
A15: Credit discount vs agency (points) | B15: =B5-B14 -> 0.10813458 | C15: Cost of replacing the government guarantee
A16: Model − market | B16: ='Private MC Output'!E7 -> 0.35157257 | C16: Still above the agency BVAL bid under historical PD
A17: Break-even annual PD | B17: 0.0042626893 | C17: PD at which private-label value = BVAL bid
A18: CHECKS
A19: Excel vs Python path 1 (agency) | B19: ='Agency CF'!S59 -> 0 | C19: Should be ~0
A20: Excel vs Python path 1 (private) | B20: ='Private CF'!H59 -> 0 | C20: Should be ~0

Sheet Inputs
A1: Input | B1: Value | C1: Source / note
A2: Security | B2: FN FS9548 Mtge | C2: Bloomberg DES
A3: CUSIP | B3: 3140XRTE5 | C3: Bloomberg DES
A4: Pool type | B4: UMBS Conventional 15-year (Super pool, FNCI 3 2015 vintage) | C4: Bloomberg DES
A5: Pass-through coupon | B5: 0.03 | C5: Bloomberg DES
A6: WAC | B6: 0.03448 | C6: Bloomberg DES
A7: WAM / WARM (months) | B7: 52 | C7: Bloomberg DES
A8: WALA (months) | B8: 125 | C8: Bloomberg DES
A9: Original amount | B9: 5238307 | C9: Bloomberg DES
A10: Current balance B0 | B10: 2986518 | C10: Bloomberg DES (04/2026 factor)
A11: Pool factor | B11: =B10/B9 -> 0.57013039 | C11: Current / original; Bloomberg shows 0.57013048
A12: Base PSA | B12: 1.78 | C12: Bloomberg BAM projection (BVAL/ALLQ screen)
A13: Refinancing sensitivity beta | B13: 0.2 | C13: PSA multiplier = 1 - beta x (rate change / 1%)
A14: Multiplier floor | B14: 0.75 | C14: Lock-in floor
A15: Multiplier cap | B15: 1.75 | C15: Refinancing cap
A16: BVAL bid (32nds) | B16: 23.625 | C16: 97-23 5/8 bid, 30 Apr 2026, NY 4pm
A17: BVAL bid (decimal, clean) | B17: =97+B16/32 -> 97.738281
A18: Accrued days (30/360) | B18: 29 | C18: 1 Apr to 30 Apr settlement
A19: Accrued interest per 100 | B19: =B5/12*B18/30*100 -> 0.24166667
A20: BVAL bid full price | B20: =B17+B19 -> 97.979948 | C20: Clean + accrued
A21: Payment lag (months after month start) | B21: 0.83333333 | C21: Paid on the 25th of the following month (54-day delay)
A22: Bloomberg BAM TOAS (bp) | B22: 17.9 | C22: Bloomberg ALLQ / DES header
A23: Monte Carlo paths | B23: 10000 | C23: 5,000 antithetic pairs, seed 2026 (Python)

Sheet Rate Volatility
A1: Month-end | B1: GT10 yield (%) | C1: Monthly change (%) | E1: Statistic | F1: Value
A2: 42521 | B2: 1.847 | E2: Monthly volatility (% points) | F2: =_xlfn.STDEV.S(C3:C121) -> 0.25205529
A3: 42551 | B3: 1.471 | C3: =B3-B2 -> -0.376 | E3: Monthly volatility (decimal) sigma | F3: =F2/100 -> 0.0025205529
A4: 42580 | B4: 1.454 | C4: =B4-B3 -> -0.017 | E4: Observations (changes) | F4: =COUNT(C3:C121) -> 119
A5: 42613 | B5: 1.581 | C5: =B5-B4 -> 0.127 | E5: Excludes the 5 May 2026 print in the raw export (after the valuation date).
A6: 42643 | B6: 1.595 | C6: =B6-B5 -> 0.014
A7: 42674 | B7: 1.826 | C7: =B7-B6 -> 0.231
A8: 42704 | B8: 2.382 | C8: =B8-B7 -> 0.556
A9: 42734 | B9: 2.445 | C9: =B9-B8 -> 0.063
A10: 42766 | B10: 2.454 | C10: =B10-B9 -> 0.009
A11: 42794 | B11: 2.391 | C11: =B11-B10 -> -0.063
A12: 42825 | B12: 2.388 | C12: =B12-B11 -> -0.003
A13: 42853 | B13: 2.281 | C13: =B13-B12 -> -0.107
A14: 42886 | B14: 2.204 | C14: =B14-B13 -> -0.077
A15: 42916 | B15: 2.305 | C15: =B15-B14 -> 0.101
A16: 42947 | B16: 2.295 | C16: =B16-B15 -> -0.01
A17: 42978 | B17: 2.118 | C17: =B17-B16 -> -0.177
... A121: 46142 | B121: 4.372 | C121: =B121-B120 -> 0.053

Sheet Yield Curve
A1: Maturity (yrs) | B1: Par yield (BEY) | C1: Discount factor | D1: Zero rate (cont.) | E1: Zero rate (BEY) | G1: Bills (<=1y) treated as zero yields; 1.5y-5y bootstrapped from linearly interpolated par yields: 1 = c*sum(P) + (1+c)*P(t_n). Monthly P(0,t) by linear interpolation of continuous zero rates.
A2: 0.25 | B2: 0.03655 | C2: 0.99098586 | D2: 0.036220038 | E2: 0.03655
A3: 0.5 | B3: 0.03673 | C3: 0.98196619 | D3: 0.0363968 | E3: 0.03673
A4: 1 | B4: 0.03704 | C4: 0.96396414 | D4: 0.036701186 | E4: 0.03704
A5: 1.5 | B5: 0.037935 | C5: 0.94516318 | D5: 0.037598457 | E5: 0.037954093
A6: 2 | B6: 0.03883 | C6: 0.9258932 | D6: 0.038498191 | E6: 0.038871108
A7: 2.5 | B7: 0.03906 | C7: 0.90772635 | D7: 0.038724927 | E7: 0.039102264
A8: 3 | B8: 0.03929 | C8: 0.88970476 | D8: 0.0389552 | E8: 0.039337052
A9: 3.5 | B9: 0.03952 | C9: 0.87183171 | D9: 0.039188248 | E9: 0.039574698
A10: 4 | B10: 0.03975 | C10: 0.85411035 | D10: 0.03942372 | E10: 0.039814843
A11: 4.5 | B11: 0.03998 | C11: 0.8365437 | D11: 0.039661449 | E11: 0.040057319
A12: 5 | B12: 0.04021 | C12: 0.81913465 | D12: 0.03990136 | E12: 0.04030205
A15: Month t | B15: P(0,t) Treasury | C15: Mean path DF (Python, 10,000 paths) | D15: Calibrated drift theta_t
A16: 0 | B16: 1 | C16: 1 | D16: 0.036274756
A17: 1 | B17: 0.99698621 | C17: 0.99698621 | D17: 0.036275293
A18: 2 | B18: 0.99398151 | C18: 0.99398151 | D18: 0.036276319
A19: 3 | B19: 0.99098586 | C19: 0.99098586 | D19: 0.036514234
A20: 4 | B20: 0.98797984 | C20: 0.98797984 | D20: 0.036634413
A21: 5 | B21: 0.98497326 | C21: 0.98497326 | D21: 0.036755189
A22: 6 | B22: 0.98196619 | C22: 0.98196619 | D22: 0.03681903
A23: 7 | B23: 0.97896336 | C23: 0.97896336 | D23: 0.036924467
A24: 8 | B24: 0.97596147 | C24: 0.97596147 | D24: 0.037030459
A25: 9 | B25: 0.97296055 | C25: 0.97296055 | D25: 0.037137134
A26: 10 | B26: 0.96996065 | C26: 0.96996065 | D26: 0.037244239
A27: 11 | B27: 0.96696184 | C27: 0.96696184 | D27: 0.037351651
... A67: 51 | B67: 0.84530651 | C67: 0.84530651 | D67: 0.042290516
A68: 52 | B68: 0.84238098 | C68: 0.84238098

Sheet PSA Model
A1: Projection month | B1: Loan age | C1: 100 PSA CPR | D1: Base PSA CPR | E1: Base SMM
A2: 1 | B2: =Inputs!$B$8+A2 -> 126 | C2: =0.06*MIN(B2,30)/30 -> 0.06 | D2: =C2*Inputs!$B$12 -> 0.1068 | E2: =1-(1-D2)^(1/12) -> 0.0093679084
A3: 2 | B3: =Inputs!$B$8+A3 -> 127 | C3: =0.06*MIN(B3,30)/30 -> 0.06 | D3: =C3*Inputs!$B$12 -> 0.1068 | E3: =1-(1-D3)^(1/12) -> 0.0093679084
A4: 3 | B4: =Inputs!$B$8+A4 -> 128 | C4: =0.06*MIN(B4,30)/30 -> 0.06 | D4: =C4*Inputs!$B$12 -> 0.1068 | E4: =1-(1-D4)^(1/12) -> 0.0093679084
A5: 4 | B5: =Inputs!$B$8+A5 -> 129 | C5: =0.06*MIN(B5,30)/30 -> 0.06 | D5: =C5*Inputs!$B$12 -> 0.1068 | E5: =1-(1-D5)^(1/12) -> 0.0093679084
A6: 5 | B6: =Inputs!$B$8+A6 -> 130 | C6: =0.06*MIN(B6,30)/30 -> 0.06 | D6: =C6*Inputs!$B$12 -> 0.1068 | E6: =1-(1-D6)^(1/12) -> 0.0093679084
A7: 6 | B7: =Inputs!$B$8+A7 -> 131 | C7: =0.06*MIN(B7,30)/30 -> 0.06 | D7: =C7*Inputs!$B$12 -> 0.1068 | E7: =1-(1-D7)^(1/12) -> 0.0093679084
A8: 7 | B8: =Inputs!$B$8+A8 -> 132 | C8: =0.06*MIN(B8,30)/30 -> 0.06 | D8: =C8*Inputs!$B$12 -> 0.1068 | E8: =1-(1-D8)^(1/12) -> 0.0093679084
A9: 8 | B9: =Inputs!$B$8+A9 -> 133 | C9: =0.06*MIN(B9,30)/30 -> 0.06 | D9: =C9*Inputs!$B$12 -> 0.1068 | E9: =1-(1-D9)^(1/12) -> 0.0093679084
A10: 9 | B10: =Inputs!$B$8+A10 -> 134 | C10: =0.06*MIN(B10,30)/30 -> 0.06 | D10: =C10*Inputs!$B$12 -> 0.1068 | E10: =1-(1-D10)^(1/12) -> 0.0093679084
A11: 10 | B11: =Inputs!$B$8+A11 -> 135 | C11: =0.06*MIN(B11,30)/30 -> 0.06 | D11: =C11*Inputs!$B$12 -> 0.1068 | E11: =1-(1-D11)^(1/12) -> 0.0093679084
A12: 11 | B12: =Inputs!$B$8+A12 -> 136 | C12: =0.06*MIN(B12,30)/30 -> 0.06 | D12: =C12*Inputs!$B$12 -> 0.1068 | E12: =1-(1-D12)^(1/12) -> 0.0093679084
A13: 12 | B13: =Inputs!$B$8+A13 -> 137 | C13: =0.06*MIN(B13,30)/30 -> 0.06 | D13: =C13*Inputs!$B$12 -> 0.1068 | E13: =1-(1-D13)^(1/12) -> 0.0093679084
... A53: 52 | B53: =Inputs!$B$8+A53 -> 177 | C53: =0.06*MIN(B53,30)/30 -> 0.06 | D53: =C53*Inputs!$B$12 -> 0.1068 | E53: =1-(1-D53)^(1/12) -> 0.0093679084

Sheet Rate Paths
A1: Month k | B1: Shock eps_k (fixed, from Python seed 2026) | C1: W_k = sum eps | D1: theta_k (calibrated drift) | E1: Rate shock sigma*W_k | F1: Short rate r_k = MAX(0, theta+sigma*W) | H1: r_k applies from month k to k+1. theta_k is solved in Python so that the average discount factor over 10,000 paths equals the Treasury P(0,k+1) (see Yield Curve sheet).
A2: 0 | B2: 0 | C2: =0 -> 0 | D2: 0.036274756 | E2: ='Rate Volatility'!$F$3*C2 -> 0 | F2: =MAX(0,D2+E2) -> 0.036274756
A3: 1 | B3: -0.79312248 | C3: =C2+B3 -> -0.79312248 | D3: 0.036275293 | E3: ='Rate Volatility'!$F$3*C3 -> -0.0019991071 | F3: =MAX(0,D3+E3) -> 0.034276186
A4: 2 | B4: 0.24057128 | C4: =C3+B4 -> -0.55255119 | D4: 0.036276319 | E4: ='Rate Volatility'!$F$3*C4 -> -0.0013927345 | F4: =MAX(0,D4+E4) -> 0.034883584
A5: 3 | B5: -1.8963263 | C5: =C4+B5 -> -2.4488775 | D5: 0.036514234 | E5: ='Rate Volatility'!$F$3*C5 -> -0.0061725253 | F5: =MAX(0,D5+E5) -> 0.030341709
A6: 4 | B6: 1.3957717 | C6: =C5+B6 -> -1.0531058 | D6: 0.036634413 | E6: ='Rate Volatility'!$F$3*C6 -> -0.0026544089 | F6: =MAX(0,D6+E6) -> 0.033980004
A7: 5 | B7: 0.63829474 | C7: =C6+B7 -> -0.41481109 | D7: 0.036755189 | E7: ='Rate Volatility'!$F$3*C7 -> -0.0010455533 | F7: =MAX(0,D7+E7) -> 0.035709636
A8: 6 | B8: -0.29204749 | C8: =C7+B8 -> -0.70685858 | D8: 0.03681903 | E8: ='Rate Volatility'!$F$3*C8 -> -0.0017816744 | F8: =MAX(0,D8+E8) -> 0.035037356
A9: 7 | B9: -0.31194933 | C9: =C8+B9 -> -1.0188079 | D9: 0.036924467 | E9: ='Rate Volatility'!$F$3*C9 -> -0.0025679592 | F9: =MAX(0,D9+E9) -> 0.034356508
A10: 8 | B10: 0.30383537 | C10: =C9+B10 -> -0.71497254 | D10: 0.037030459 | E10: ='Rate Volatility'!$F$3*C10 -> -0.0018021261 | F10: =MAX(0,D10+E10) -> 0.035228333
A11: 9 | B11: -0.2676603 | C11: =C10+B11 -> -0.98263284 | D11: 0.037137134 | E11: ='Rate Volatility'!$F$3*C11 -> -0.002476778 | F11: =MAX(0,D11+E11) -> 0.034660356
A12: 10 | B12: -0.22590886 | C12: =C11+B12 -> -1.2085417 | D12: 0.037244239 | E12: ='Rate Volatility'!$F$3*C12 -> -0.0030461932 | F12: =MAX(0,D12+E12) -> 0.034198046
A13: 11 | B13: 0.72006782 | C13: =C12+B13 -> -0.48847388 | D13: 0.037351651 | E13: ='Rate Volatility'!$F$3*C13 -> -0.0012312242 | F13: =MAX(0,D13+E13) -> 0.036120427
A14: 12 | B14: 0.51470521 | C14: =C13+B14 -> 0.026231327 | D14: 0.038748446 | E14: ='Rate Volatility'!$F$3*C14 -> 6.6117445e-05 | F14: =MAX(0,D14+E14) -> 0.038814564
... A53: 51 | B53: 1.6184131 | C53: =C52+B53 -> 12.472342 | D53: 0.042290516 | E53: ='Rate Volatility'!$F$3*C53 -> 0.031437196 | F53: =MAX(0,D53+E53) -> 0.073727712

Sheet Agency CF
A1: Month | B1: Beginning balance | C1: Remaining term | D1: Scheduled payment (WAC) | E1: Gross interest (WAC) | F1: Investor interest (PTR) | G1: Scheduled principal | H1: Rate shock at month start | I1: PSA multiplier | J1: CPR | K1: SMM | L1: Prepayment | M1: Total principal | N1: Ending balance | O1: Total cash flow | P1: Short rate r_(t-1) | Q1: DF to end of month t-1 | R1: DF on payment date | S1: Present value
A2: 1 | B2: =Inputs!$B$10 -> 2986518 | C2: =Inputs!$B$7-A2+1 -> 52 | D2: =B2*(Inputs!$B$6/12)/(1-(1+Inputs!$B$6/12)^(-C2)) -> 61912.795 | E2: =B2*Inputs!$B$6/12 -> 8581.2617 | F2: =B2*Inputs!$B$5/12 -> 7466.295 | G2: =MIN(D2-E2,B2) -> 53331.534 | H2: ='Rate Paths'!E2 -> 0 | I2: =MIN(Inputs!$B$15,MAX(Inputs!$B$14,1-Inputs!$B$13*H2/0.01)) -> 1 | J2: =MIN('PSA Model'!D2*I2,0.999) -> 0.1068 | K2: =1-(1-J2)^(1/12) -> 0.0093679084 | L2: =K2*(B2-G2) -> 27477.822 | M2: =G2+L2 -> 80809.356 | N2: =MAX(B2-M2,0) -> 2905708.6 | O2: =F2+M2 -> 88275.651 | P2: ='Rate Paths'!F2 -> 0.036274756 | Q2: =1 -> 1 | R2: =Q2*(1+P2/12)^(-Inputs!$B$21) -> 0.99748788 | S2: =O2*R2 -> 88053.892
A3: 2 | B3: =N2 -> 2905708.6 | C3: =Inputs!$B$7-A3+1 -> 51 | D3: =B3*(Inputs!$B$6/12)/(1-(1+Inputs!$B$6/12)^(-C3)) -> 61332.802 | E3: =B3*Inputs!$B$6/12 -> 8349.0695 | F3: =B3*Inputs!$B$5/12 -> 7264.2716 | G3: =MIN(D3-E3,B3) -> 52983.733 | H3: ='Rate Paths'!E3 -> -0.0019991071 | I3: =MIN(Inputs!$B$15,MAX(Inputs!$B$14,1-Inputs!$B$13*H3/0.01)) -> 1.0399821 | J3: =MIN('PSA Model'!D3*I3,0.999) -> 0.11107009 | K3: =1-(1-J3)^(1/12) -> 0.0097634328 | L3: =K3*(B3-G3) -> 27852.388 | M3: =G3+L3 -> 80836.12 | N3: =MAX(B3-M3,0) -> 2824872.5 | O3: =F3+M3 -> 88100.392 | P3: ='Rate Paths'!F3 -> 0.034276186 | Q3: =Q2/(1+P2/12) -> 0.99698621 | R3: =Q3*(1+P3/12)^(-Inputs!$B$21) -> 0.99461929 | S3: =O3*R3 -> 87626.35
A4: 3 | B4: =N3 -> 2824872.5 | C4: =Inputs!$B$7-A4+1 -> 50 | D4: =B4*(Inputs!$B$6/12)/(1-(1+Inputs!$B$6/12)^(-C4)) -> 60733.983 | E4: =B4*Inputs!$B$6/12 -> 8116.8004 | F4: =B4*Inputs!$B$5/12 -> 7062.1813 | G4: =MIN(D4-E4,B4) -> 52617.183 | H4: ='Rate Paths'!E4 -> -0.0013927345 | I4: =MIN(Inputs!$B$15,MAX(Inputs!$B$14,1-Inputs!$B$13*H4/0.01)) -> 1.0278547 | J4: =MIN('PSA Model'!D4*I4,0.999) -> 0.10977488 | K4: =1-(1-J4)^(1/12) -> 0.0096432779 | L4: =K4*(B4-G4) -> 26733.629 | M4: =G4+L4 -> 79350.812 | N4: =MAX(B4-M4,0) -> 2745521.7 | O4: =F4+M4 -> 86412.993 | P4: ='Rate Paths'!F4 -> 0.034883584 | Q4: =Q3/(1+P3/12) -> 0.99414658 | R4: =Q4*(1+P4/12)^(-Inputs!$B$21) -> 0.99174469 | S4: =O4*R4 -> 85699.627
A5: 4 | B5: =N4 -> 2745521.7 | C5: =Inputs!$B$7-A5+1 -> 49 | D5: =B5*(Inputs!$B$6/12)/(1-(1+Inputs!$B$6/12)^(-C5)) -> 60148.309 | E5: =B5*Inputs!$B$6/12 -> 7888.7991 | F5: =B5*Inputs!$B$5/12 -> 6863.8043 | G5: =MIN(D5-E5,B5) -> 52259.51 | H5: ='Rate Paths'!E5 -> -0.0061725253 | I5: =MIN(Inputs!$B$15,MAX(Inputs!$B$14,1-Inputs!$B$13*H5/0.01)) -> 1.1234505 | J5: =MIN('PSA Model'!D5*I5,0.999) -> 0.11998451 | K5: =1-(1-J5)^(1/12) -> 0.01059479 | L5: =K5*(B5-G5) -> 28534.548 | M5: =G5+L5 -> 80794.057 | N5: =MAX(B5-M5,0) -> 2664727.7 | O5: =F5+M5 -> 87657.862 | P5: ='Rate Paths'!F5 -> 0.030341709 | Q5: =Q4/(1+P4/12) -> 0.99126501 | R5: =Q5*(1+P5/12)^(-Inputs!$B$21) -> 0.98918118 | S5: =O5*R5 -> 86709.507
A6: 5 | B6: =N5 -> 2664727.7 | C6: =Inputs!$B$7-A6+1 -> 48 | D6: =B6*(Inputs!$B$6/12)/(1-(1+Inputs!$B$6/12)^(-C6)) -> 59511.05 | E6: =B6*Inputs!$B$6/12 -> 7656.6508 | F6: =B6*Inputs!$B$5/12 -> 6661.8191 | G6: =MIN(D6-E6,B6) -> 51854.399 | H6: ='Rate Paths'!E6 -> -0.0026544089 | I6: =MIN(Inputs!$B$15,MAX(Inputs!$B$14,1-Inputs!$B$13*H6/0.01)) -> 1.0530882 | J6: =MIN('PSA Model'!D6*I6,0.999) -> 0.11246982 | K6: =1-(1-J6)^(1/12) -> 0.0098934636 | L6: =K6*(B6-G6) -> 25850.367 | M6: =G6+L6 -> 77704.766 | N6: =MAX(B6-M6,0) -> 2587022.9 | O6: =F6+M6 -> 84366.585 | P6: ='Rate Paths'!F6 -> 0.033980004 | Q6: =Q5/(1+P5/12) -> 0.98876494 | R6: =Q6*(1+P6/12)^(-Inputs!$B$21) -> 0.98643777 | S6: =O6*R6 -> 83222.386
A7: 6 | B7: =N6 -> 2587022.9 | C7: =Inputs!$B$7-A7+1 -> 47 | D7: =B7*(Inputs!$B$6/12)/(1-(1+Inputs!$B$6/12)^(-C7)) -> 58922.28 | E7: =B7*Inputs!$B$6/12 -> 7433.3791 | F7: =B7*Inputs!$B$5/12 -> 6467.5572 | G7: =MIN(D7-E7,B7) -> 51488.9 | H7: ='Rate Paths'!E7 -> -0.0010455533 | I7: =MIN(Inputs!$B$15,MAX(Inputs!$B$14,1-Inputs!$B$13*H7/0.01)) -> 1.0209111 | J7: =MIN('PSA Model'!D7*I7,0.999) -> 0.1090333 | K7: =1-(1-J7)^(1/12) -> 0.0095745549 | L7: =K7*(B7-G7) -> 24276.609 | M7: =G7+L7 -> 75765.51 | N7: =MAX(B7-M7,0) -> 2511257.4 | O7: =F7+M7 -> 82233.067 | P7: ='Rate Paths'!F7 -> 0.035709636 | Q7: =Q6/(1+P6/12) -> 0.985973 | R7: =Q7*(1+P7/12)^(-Inputs!$B$21) -> 0.9835346 | S7: =O7*R7 -> 80879.066
A8: 7 | B8: =N7 -> 2511257.4 | C8: =Inputs!$B$7-A8+1 -> 46 | D8: =B8*(Inputs!$B$6/12)/(1-(1+Inputs!$B$6/12)^(-C8)) -> 58358.125 | E8: =B8*Inputs!$B$6/12 -> 7215.6795 | F8: =B8*Inputs!$B$5/12 -> 6278.1434 | G8: =MIN(D8-E8,B8) -> 51142.445 | H8: ='Rate Paths'!E8 -> -0.0017816744 | I8: =MIN(Inputs!$B$15,MAX(Inputs!$B$14,1-Inputs!$B$13*H8/0.01)) -> 1.0356335 | J8: =MIN('PSA Model'!D8*I8,0.999) -> 0.11060566 | K8: =1-(1-J8)^(1/12) -> 0.0097203293 | L8: =K8*(B8-G8) -> 23913.127 | M8: =G8+L8 -> 75055.573 | N8: =MAX(B8-M8,0) -> 2436201.8 | O8: =F8+M8 -> 81333.716 | P8: ='Rate Paths'!F8 -> 0.035037356 | Q8: =Q7/(1+P7/12) -> 0.98304764 | R8: =Q8*(1+P8/12)^(-Inputs!$B$21) -> 0.98066212 | S8: =O8*R8 -> 79760.895
A9: 8 | B9: =N8 -> 2436201.8 | C9: =Inputs!$B$7-A9+1 -> 45 | D9: =B9*(Inputs!$B$6/12)/(1-(1+Inputs!$B$6/12)^(-C9)) -> 57790.865 | E9: =B9*Inputs!$B$6/12 -> 7000.0199 | F9: =B9*Inputs!$B$5/12 -> 6090.5045 | G9: =MIN(D9-E9,B9) -> 50790.845 | H9: ='Rate Paths'!E9 -> -0.0025679592 | I9: =MIN(Inputs!$B$15,MAX(Inputs!$B$14,1-Inputs!$B$13*H9/0.01)) -> 1.0513592 | J9: =MIN('PSA Model'!D9*I9,0.999) -> 0.11228516 | K9: =1-(1-J9)^(1/12) -> 0.0098762987 | L9: =K9*(B9-G9) -> 23559.031 | M9: =G9+L9 -> 74349.876 | N9: =MAX(B9-M9,0) -> 2361851.9 | O9: =F9+M9 -> 80440.381 | P9: ='Rate Paths'!F9 -> 0.034356508 | Q9: =Q8/(1+P8/12) -> 0.98018571 | R9: =Q9*(1+P9/12)^(-Inputs!$B$21) -> 0.97785324 | S9: =O9*R9 -> 78658.887
A10: 9 | B10: =N9 -> 2361851.9 | C10: =Inputs!$B$7-A10+1 -> 44 | D10: =B10*(Inputs!$B$6/12)/(1-(1+Inputs!$B$6/12)^(-C10)) -> 57220.105 | E10: =B10*Inputs!$B$6/12 -> 6786.3879 | F10: =B10*Inputs!$B$5/12 -> 5904.6298 | G10: =MIN(D10-E10,B10) -> 50433.717 | H10: ='Rate Paths'!E10 -> -0.0018021261 | I10: =MIN(Inputs!$B$15,MAX(Inputs!$B$14,1-Inputs!$B$13*H10/0.01)) -> 1.0360425 | J10: =MIN('PSA Model'!D10*I10,0.999) -> 0.11064934 | K10: =1-(1-J10)^(1/12) -> 0.0097243827 | L10: =K10*(B10-G10) -> 22477.115 | M10: =G10+L10 -> 72910.832 | N10: =MAX(B10-M10,0) -> 2288941.1 | O10: =F10+M10 -> 78815.462 | P10: ='Rate Paths'!F10 -> 0.035228333 | Q10: =Q9/(1+P9/12) -> 0.97738741 | R10: =Q10*(1+P10/12)^(-Inputs!$B$21) -> 0.97500274 | S10: =O10*R10 -> 76845.291
A11: 10 | B11: =N10 -> 2288941.1 | C11: =Inputs!$B$7-A11+1 -> 43 | D11: =B11*(Inputs!$B$6/12)/(1-(1+Inputs!$B$6/12)^(-C11)) -> 56663.675 | E11: =B11*Inputs!$B$6/12 -> 6576.8908 | F11: =B11*Inputs!$B$5/12 -> 5722.3527 | G11: =MIN(D11-E11,B11) -> 50086.784 | H11: ='Rate Paths'!E11 -> -0.002476778 | I11: =MIN(Inputs!$B$15,MAX(Inputs!$B$14,1-Inputs!$B$13*H11/0.01)) -> 1.0495356 | J11: =MIN('PSA Model'!D11*I11,0.999) -> 0.1120904 | K11: =1-(1-J11)^(1/12) -> 0.0098581979 | L11: =K11*(B11-G11) -> 22071.069 | M11: =G11+L11 -> 72157.853 | N11: =MAX(B11-M11,0) -> 2216783.2 | O11: =F11+M11 -> 77880.206 | P11: ='Rate Paths'!F11 -> 0.034660356 | Q11: =Q10/(1+P10/12) -> 0.9745265 | R11: =Q11*(1+P11/12)^(-Inputs!$B$21) -> 0.97218704 | S11: =O11*R11 -> 75714.127
A12: 11 | B12: =N11 -> 2216783.2 | C12: =Inputs!$B$7-A12+1 -> 42 | D12: =B12*(Inputs!$B$6/12)/(1-(1+Inputs!$B$6/12)^(-C12)) -> 56105.073 | E12: =B12*Inputs!$B$6/12 -> 6369.5572 | F12: =B12*Inputs!$B$5/12 -> 5541.9581 | G12: =MIN(D12-E12,B12) -> 49735.516 | H12: ='Rate Paths'!E12 -> -0.0030461932 | I12: =MIN(Inputs!$B$15,MAX(Inputs!$B$14,1-Inputs!$B$13*H12/0.01)) -> 1.0609239 | J12: =MIN('PSA Model'!D12*I12,0.999) -> 0.11330667 | K12: =1-(1-J12)^(1/12) -> 0.0099712948 | L12: =K12*(B12-G12) -> 21608.272 | M12: =G12+L12 -> 71343.788 | N12: =MAX(B12-M12,0) -> 2145439.5 | O12: =F12+M12 -> 76885.746 | P12: ='Rate Paths'!F12 -> 0.034198046 | Q12: =Q11/(1+P11/12) -> 0.97171982 | R12: =Q12*(1+P12/12)^(-Inputs!$B$21) -> 0.96941813 | S12: =O12*R12 -> 74534.436
A13: 12 | B13: =N12 -> 2145439.5 | C13: =Inputs!$B$7-A13+1 -> 41 | D13: =B13*(Inputs!$B$6/12)/(1-(1+Inputs!$B$6/12)^(-C13)) -> 55545.633 | E13: =B13*Inputs!$B$6/12 -> 6164.5627 | F13: =B13*Inputs!$B$5/12 -> 5363.5986 | G13: =MIN(D13-E13,B13) -> 49381.07 | H13: ='Rate Paths'!E13 -> -0.0012312242 | I13: =MIN(Inputs!$B$15,MAX(Inputs!$B$14,1-Inputs!$B$13*H13/0.01)) -> 1.0246245 | J13: =MIN('PSA Model'!D13*I13,0.999) -> 0.10942989 | K13: =1-(1-J13)^(1/12) -> 0.0096113012 | L13: =K13*(B13-G13) -> 20145.848 | M13: =G13+L13 -> 69526.919 | N13: =MAX(B13-M13,0) -> 2075912.5 | O13: =F13+M13 -> 74890.517 | P13: ='Rate Paths'!F13 -> 0.036120427 | Q13: =Q12/(1+P12/12) -> 0.96895845 | R13: =Q13*(1+P13/12)^(-Inputs!$B$21) -> 0.96653463 | S13: =O13*R13 -> 72384.279
A14: 13 | B14: =N13 -> 2075912.5 | C14: =Inputs!$B$7-A14+1 -> 40 | D14: =B14*(Inputs!$B$6/12)/(1-(1+Inputs!$B$6/12)^(-C14)) -> 55011.767 | E14: =B14*Inputs!$B$6/12 -> 5964.7887 | F14: =B14*Inputs!$B$5/12 -> 5189.7813 | G14: =MIN(D14-E14,B14) -> 49046.978 | H14: ='Rate Paths'!E14 -> 6.6117445e-05 | I14: =MIN(Inputs!$B$15,MAX(Inputs!$B$14,1-Inputs!$B$13*H14/0.01)) -> 0.99867765 | J14: =MIN('PSA Model'!D14*I14,0.999) -> 0.10665877 | K14: =1-(1-J14)^(1/12) -> 0.0093548567 | L14: =K14*(B14-G14) -> 18961.037 | M14: =G14+L14 -> 68008.015 | N14: =MAX(B14-M14,0) -> 2007904.5 | O14: =F14+M14 -> 73197.796 | P14: ='Rate Paths'!F14 -> 0.038814564 | Q14: =Q13/(1+P13/12) -> 0.9660506 | R14: =Q14*(1+P14/12)^(-Inputs!$B$21) -> 0.96345435 | S14: =O14*R14 -> 70522.735
... A53: 52 | B53: =N52 -> 38593.437 | C53: =Inputs!$B$7-A53+1 -> 1 | D53: =B53*(Inputs!$B$6/12)/(1-(1+Inputs!$B$6/12)^(-C53)) -> 38704.329 | E53: =B53*Inputs!$B$6/12 -> 110.89181 | F53: =B53*Inputs!$B$5/12 -> 96.483592 | G53: =MIN(D53-E53,B53) -> 38593.437 | H53: ='Rate Paths'!E53 -> 0.031437196 | I53: =MIN(Inputs!$B$15,MAX(Inputs!$B$14,1-Inputs!$B$13*H53/0.01)) -> 0.75 | J53: =MIN('PSA Model'!D53*I53,0.999) -> 0.0801 | K53: =1-(1-J53)^(1/12) -> 0.0069333783 | L53: =K53*(B53-G53) -> 0 | M53: =G53+L53 -> 38593.437 | N53: =MAX(B53-M53,0) -> 0 | O53: =F53+M53 -> 38689.92 | P53: ='Rate Paths'!F53 -> 0.073727712 | Q53: =Q52/(1+P52/12) -> 0.83913436 | R53: =Q53*(1+P53/12)^(-Inputs!$B$21) -> 0.83486207 | S53: =O53*R53 -> 32300.747
Q55: Total PV ($) | S55: =SUM(S2:S53) -> 2947189.9
Q56: Path 1 full price per 100 | S56: =S55/Inputs!$B$10*100 -> 98.683145
Q57: Path 1 clean price per 100 | S57: =S56-Inputs!$B$19 -> 98.441479
Q58: Python path 1 full price | S58: 98.683145
Q59: Check: Excel − Python (should be ~0) | S59: =S56-S58 -> 0
A61: One path only. The model value is the average over 10,000 paths: see Agency MC Output. DF on payment date = DF(end of month t-1) x (1+r_(t-1)/12)^(-25/30).

Sheet Credit Risk
A1: Input | B1: Value | C1: Note | E1: Month t | F1: Survival S_t | G1: Marginal default S_(t-1) - S_t
A2: Guarantor rating | B2: A (S&P) | C2: Hypothetical private guarantor | E2: 0 | F2: 1
A3: Annual probability of default | B3: 0.001 | C3: S&P long-run 'A' default experience, ~0.1%/yr over 4-5 yrs | E3: 1 | F3: =(1-$B$3)^(E3/12) -> 0.99991663 | G3: =F2-F3 -> 8.3371552e-05
A4: Recovery rate | B4: 0.4 | C4: Senior unsecured assumption | E4: 2 | F4: =(1-$B$3)^(E4/12) -> 0.99983326 | G4: =F3-F4 -> 8.3364601e-05
A5: Loss given default | B5: =1-B4 -> 0.6 | E5: 3 | F5: =(1-$B$3)^(E5/12) -> 0.99974991 | G5: =F4-F5 -> 8.3357651e-05
A6: Monthly PD | B6: =1-(1-B3)^(1/12) -> 8.3371552e-05 | E6: 4 | F6: =(1-$B$3)^(E6/12) -> 0.99966656 | G6: =F5-F6 -> 8.3350701e-05
E7: 5 | F7: =(1-$B$3)^(E7/12) -> 0.99958321 | G7: =F6-F7 -> 8.3343752e-05
E8: 6 | F8: =(1-$B$3)^(E8/12) -> 0.99949987 | G8: =F7-F8 -> 8.3336804e-05
E9: 7 | F9: =(1-$B$3)^(E9/12) -> 0.99941655 | G9: =F8-F9 -> 8.3329856e-05
E10: 8 | F10: =(1-$B$3)^(E10/12) -> 0.99933322 | G10: =F9-F10 -> 8.3322909e-05
E11: 9 | F11: =(1-$B$3)^(E11/12) -> 0.99924991 | G11: =F10-F11 -> 8.3315962e-05
E12: 10 | F12: =(1-$B$3)^(E12/12) -> 0.9991666 | G12: =F11-F12 -> 8.3309016e-05
E13: 11 | F13: =(1-$B$3)^(E13/12) -> 0.9990833 | G13: =F12-F13 -> 8.330207e-05
E14: 12 | F14: =(1-$B$3)^(E14/12) -> 0.999 | G14: =F13-F14 -> 8.3295125e-05
E15: 13 | F15: =(1-$B$3)^(E15/12) -> 0.99891671 | G15: =F14-F15 -> 8.3288181e-05
E16: 14 | F16: =(1-$B$3)^(E16/12) -> 0.99883343 | G16: =F15-F16 -> 8.3281237e-05
E17: 15 | F17: =(1-$B$3)^(E17/12) -> 0.99875016 | G17: =F16-F17 -> 8.3274293e-05
E18: 16 | F18: =(1-$B$3)^(E18/12) -> 0.99866689 | G18: =F17-F18 -> 8.3267351e-05
... E54: 52 | F54: =(1-$B$3)^(E54/12) -> 0.99567388 | G54: =F53-F54 -> 8.3017798e-05

Sheet Private CF
A1: Month | B1: Promised cash flow (Agency CF) | C1: Beginning balance B_(t-1) | D1: Survival S_t | E1: Marginal default | F1: Expected cash flow | G1: DF on payment date | H1: Credit-adjusted PV
A2: 1 | B2: ='Agency CF'!O2 -> 88275.651 | C2: ='Agency CF'!B2 -> 2986518 | D2: ='Credit Risk'!F3 -> 0.99991663 | E2: ='Credit Risk'!G3 -> 8.3371552e-05 | F2: =D2*B2+E2*'Credit Risk'!$B$4*C2 -> 88367.888 | G2: ='Agency CF'!R2 -> 0.99748788 | H2: =F2*G2 -> 88145.897
A3: 2 | B3: ='Agency CF'!O3 -> 88100.392 | C3: ='Agency CF'!B3 -> 2905708.6 | D3: ='Credit Risk'!F4 -> 0.99983326 | E3: ='Credit Risk'!G4 -> 8.3364601e-05 | F3: =D3*B3+E3*'Credit Risk'!$B$4*C3 -> 88182.596 | G3: ='Agency CF'!R3 -> 0.99461929 | H3: =F3*G3 -> 87708.111
A4: 3 | B4: ='Agency CF'!O4 -> 86412.993 | C4: ='Agency CF'!B4 -> 2824872.5 | D4: ='Credit Risk'!F5 -> 0.99974991 | E4: ='Credit Risk'!G5 -> 8.3357651e-05 | F4: =D4*B4+E4*'Credit Risk'!$B$4*C4 -> 86485.572 | G4: ='Agency CF'!R4 -> 0.99174469 | H4: =F4*G4 -> 85771.607
A5: 4 | B5: ='Agency CF'!O5 -> 87657.862 | C5: ='Agency CF'!B5 -> 2745521.7 | D5: ='Credit Risk'!F6 -> 0.99966656 | E5: ='Credit Risk'!G6 -> 8.3350701e-05 | F5: =D5*B5+E5*'Credit Risk'!$B$4*C5 -> 87720.169 | G5: ='Agency CF'!R5 -> 0.98918118 | H5: =F5*G5 -> 86771.141
A6: 5 | B6: ='Agency CF'!O6 -> 84366.585 | C6: ='Agency CF'!B6 -> 2664727.7 | D6: ='Credit Risk'!F7 -> 0.99958321 | E6: ='Credit Risk'!G7 -> 8.3343752e-05 | F6: =D6*B6+E6*'Credit Risk'!$B$4*C6 -> 84420.257 | G6: ='Agency CF'!R6 -> 0.98643777 | H6: =F6*G6 -> 83275.33
A7: 6 | B7: ='Agency CF'!O7 -> 82233.067 | C7: ='Agency CF'!B7 -> 2587022.9 | D7: ='Credit Risk'!F8 -> 0.99949987 | E7: ='Credit Risk'!G8 -> 8.3336804e-05 | F7: =D7*B7+E7*'Credit Risk'!$B$4*C7 -> 82278.178 | G7: ='Agency CF'!R7 -> 0.9835346 | H7: =F7*G7 -> 80923.435
A8: 7 | B8: ='Agency CF'!O8 -> 81333.716 | C8: ='Agency CF'!B8 -> 2511257.4 | D8: ='Credit Risk'!F9 -> 0.99941655 | E8: ='Credit Risk'!G9 -> 8.3329856e-05 | F8: =D8*B8+E8*'Credit Risk'!$B$4*C8 -> 81369.967 | G8: ='Agency CF'!R8 -> 0.98066212 | H8: =F8*G8 -> 79796.444
A9: 8 | B9: ='Agency CF'!O9 -> 80440.381 | C9: ='Agency CF'!B9 -> 2436201.8 | D9: ='Credit Risk'!F10 -> 0.99933322 | E9: ='Credit Risk'!G10 -> 8.3322909e-05 | F9: =D9*B9+E9*'Credit Risk'!$B$4*C9 -> 80467.941 | G9: ='Agency CF'!R9 -> 0.97785324 | H9: =F9*G9 -> 78685.837
A10: 9 | B10: ='Agency CF'!O10 -> 78815.462 | C10: ='Agency CF'!B10 -> 2361851.9 | D10: ='Credit Risk'!F11 -> 0.99924991 | E10: ='Credit Risk'!G11 -> 8.3315962e-05 | F10: =D10*B10+E10*'Credit Risk'!$B$4*C10 -> 78835.055 | G10: ='Agency CF'!R10 -> 0.97500274 | H10: =F10*G10 -> 76864.395
A11: 10 | B11: ='Agency CF'!O11 -> 77880.206 | C11: ='Agency CF'!B11 -> 2288941.1 | D11: ='Credit Risk'!F12 -> 0.9991666 | E11: ='Credit Risk'!G12 -> 8.3309016e-05 | F11: =D11*B11+E11*'Credit Risk'!$B$4*C11 -> 77891.576 | G11: ='Agency CF'!R11 -> 0.97218704 | H11: =F11*G11 -> 75725.181
A12: 11 | B12: ='Agency CF'!O12 -> 76885.746 | C12: ='Agency CF'!B12 -> 2216783.2 | D12: ='Credit Risk'!F13 -> 0.9990833 | E12: ='Credit Risk'!G13 -> 8.330207e-05 | F12: =D12*B12+E12*'Credit Risk'!$B$4*C12 -> 76889.129 | G12: ='Agency CF'!R12 -> 0.96941813 | H12: =F12*G12 -> 74537.716
A13: 12 | B13: ='Agency CF'!O13 -> 74890.517 | C13: ='Agency CF'!B13 -> 2145439.5 | D13: ='Credit Risk'!F14 -> 0.999 | E13: ='Credit Risk'!G14 -> 8.3295125e-05 | F13: =D13*B13+E13*'Credit Risk'!$B$4*C13 -> 74887.108 | G13: ='Agency CF'!R13 -> 0.96653463 | H13: =F13*G13 -> 72380.984
... A53: 52 | B53: ='Agency CF'!O53 -> 38689.92 | C53: ='Agency CF'!B53 -> 38593.437 | D53: ='Credit Risk'!F54 -> 0.99567388 | E53: ='Credit Risk'!G54 -> 8.3017798e-05 | F53: =D53*B53+E53*'Credit Risk'!$B$4*C53 -> 38523.825 | G53: ='Agency CF'!R53 -> 0.83486207 | H53: =F53*G53 -> 32162.08
G55: Total PV ($) | H55: =SUM(H2:H53) -> 2943965.1
G56: Path 1 full price per 100 | H56: =H55/Inputs!$B$10*100 -> 98.575166
G57: Path 1 clean price per 100 | H57: =H56-Inputs!$B$19 -> 98.333499
G58: Python path 1 full price | H58: 98.575166
G59: Check: Excel − Python (should be ~0) | H59: =H56-H58 -> 0
A61: E[CF_t] = S_t x CF_t + (S_(t-1) - S_t) x R x B_(t-1): recovery is on the outstanding principal claim.

Sheet Agency MC Output
A1: Path | B1: Full price per 100 | C1: Antithetic pair average (path i and i+5,000) | D1: Summary | E1: Value
A2: 1 | B2: 98.683145 | C2: =(B2+B5002)/2 -> 98.454695 | D2: Average full price | E2: =AVERAGE(B2:B10001) -> 98.439655
A3: 2 | B3: 99.628708 | C3: =(B3+B5003)/2 -> 98.438643 | D3: Accrued interest | E3: =Inputs!$B$19 -> 0.24166667
A4: 3 | B4: 97.126399 | C4: =(B4+B5004)/2 -> 98.437599 | D4: Average clean price | E4: =E2-E3 -> 98.197988
A5: 4 | B5: 96.362252 | C5: =(B5+B5005)/2 -> 98.41853 | D5: Std error (antithetic pairs) | E5: =_xlfn.STDEV.S(C2:C5001)/SQRT(5000) -> 0.00026981306
A6: 5 | B6: 99.443416 | C6: =(B6+B5006)/2 -> 98.451334 | D6: BVAL bid (clean) | E6: =Inputs!$B$17 -> 97.738281
A7: 6 | B7: 99.744283 | C7: =(B7+B5007)/2 -> 98.445201 | D7: Model − market | E7: =E4-E6 -> 0.45970715
A8: 7 | B8: 100.33855 | C8: =(B8+B5008)/2 -> 98.419158 | D8: Conclusion | E8: =IF(E7>0,"Model above market: cheap vs Treasuries at zero OAS","Model below market: rich") -> Model above market: cheap vs Treasuries at zero OAS
A9: 8 | B9: 98.67277 | C9: =(B9+B5009)/2 -> 98.454995
A10: 9 | B10: 96.599682 | C10: =(B10+B5010)/2 -> 98.43003 | D10: Paths 1-5,000 and 5,001-10,000 are antithetic pairs (shocks eps and -eps).
A11: 10 | B11: 98.667178 | C11: =(B11+B5011)/2 -> 98.454163
A12: 11 | B12: 97.162979 | C12: =(B12+B5012)/2 -> 98.442033
A13: 12 | B13: 99.433875 | C13: =(B13+B5013)/2 -> 98.44498
A14: 13 | B14: 99.298661 | C14: =(B14+B5014)/2 -> 98.446335
A15: 14 | B15: 96.299342 | C15: =(B15+B5015)/2 -> 98.41371
A16: 15 | B16: 98.140163 | C16: =(B16+B5016)/2 -> 98.453271
A17: 16 | B17: 97.406013 | C17: =(B17+B5017)/2 -> 98.44307
A18: 17 | B18: 98.983366 | C18: =(B18+B5018)/2 -> 98.454692
A19: 18 | B19: 96.5007 | C19: =(B19+B5019)/2 -> 98.420932
A20: 19 | B20: 101.31234 | C20: =(B20+B5020)/2 -> 98.403378
A21: 20 | B21: 99.083356 | C21: =(B21+B5021)/2 -> 98.451139
A22: 21 | B22: 98.250351 | C22: =(B22+B5022)/2 -> 98.454692
... A5001: 5000 | B5001: 99.147417 | C5001: =(B5001+B10001)/2 -> 98.446823
A5002: 5001 | B5002: 98.226244
A5003: 5002 | B5003: 97.248578
A5004: 5003 | B5004: 99.748799
A5005: 5004 | B5005: 100.47481
A5006: 5005 | B5006: 97.459253
A5007: 5006 | B5007: 97.146119
A5008: 5007 | B5008: 96.499769
A5009: 5008 | B5009: 98.23722
A5010: 5009 | B5010: 100.26038
A5011: 5010 | B5011: 98.241148
A5012: 5011 | B5012: 99.721088
A5013: 5012 | B5013: 97.456086
... A10001: 10000 | B10001: 97.74623

Sheet Private MC Output
A1: Path | B1: Full price per 100 | C1: Antithetic pair average (path i and i+5,000) | D1: Summary | E1: Value
A2: 1 | B2: 98.575166 | C2: =(B2+B5002)/2 -> 98.346386 | D2: Average full price | E2: =AVERAGE(B2:B10001) -> 98.33152
A3: 2 | B3: 99.519021 | C3: =(B3+B5003)/2 -> 98.330435 | D3: Accrued interest | E3: =Inputs!$B$19 -> 0.24166667
A4: 3 | B4: 97.019463 | C4: =(B4+B5004)/2 -> 98.329406 | D4: Average clean price | E4: =E2-E3 -> 98.089854
A5: 4 | B5: 96.257508 | C5: =(B5+B5005)/2 -> 98.310738 | D5: Std error (antithetic pairs) | E5: =_xlfn.STDEV.S(C2:C5001)/SQRT(5000) -> 0.00026628156
A6: 5 | B6: 99.334533 | C6: =(B6+B5006)/2 -> 98.343279 | D6: BVAL bid (clean) | E6: =Inputs!$B$17 -> 97.738281
A7: 6 | B7: 99.636486 | C7: =(B7+B5007)/2 -> 98.337036 | D7: Model − market | E7: =E4-E6 -> 0.35157257
A8: 7 | B8: 100.22822 | C8: =(B8+B5008)/2 -> 98.311167 | D8: Conclusion | E8: =IF(E7>0,"Model above market: cheap vs Treasuries at zero OAS","Model below market: rich") -> Model above market: cheap vs Treasuries at zero OAS
A9: 8 | B9: 98.56441 | C9: =(B9+B5009)/2 -> 98.346689
A10: 9 | B10: 96.493013 | C10: =(B10+B5010)/2 -> 98.322036 | D10: Paths 1-5,000 and 5,001-10,000 are antithetic pairs (shocks eps and -eps).
A11: 10 | B11: 98.558226 | C11: =(B11+B5011)/2 -> 98.345865
A12: 11 | B12: 97.054911 | C12: =(B12+B5012)/2 -> 98.33379
A13: 12 | B13: 99.324889 | C13: =(B13+B5013)/2 -> 98.336707
A14: 13 | B14: 99.188919 | C14: =(B14+B5014)/2 -> 98.338142
A15: 14 | B15: 96.193403 | C15: =(B15+B5015)/2 -> 98.305727
A16: 15 | B16: 98.032558 | C16: =(B16+B5016)/2 -> 98.344969
A17: 16 | B17: 97.298811 | C17: =(B17+B5017)/2 -> 98.334822
A18: 17 | B18: 98.875947 | C18: =(B18+B5018)/2 -> 98.346444
A19: 18 | B19: 96.394489 | C19: =(B19+B5019)/2 -> 98.312903
A20: 19 | B20: 101.20224 | C20: =(B20+B5020)/2 -> 98.295995
A21: 20 | B21: 98.974548 | C21: =(B21+B5021)/2 -> 98.342855
A22: 21 | B22: 98.142261 | C22: =(B22+B5022)/2 -> 98.346384
... A5001: 5000 | B5001: 99.037286 | C5001: =(B5001+B10001)/2 -> 98.338628
A5002: 5001 | B5002: 98.117606
A5003: 5002 | B5003: 97.141849
A5004: 5003 | B5004: 99.639349
A5005: 5004 | B5005: 100.36397
A5006: 5005 | B5006: 97.352026
A5007: 5006 | B5007: 97.037585
A5008: 5007 | B5008: 96.394116
A5009: 5008 | B5009: 98.128968
A5010: 5009 | B5010: 100.15106
A5011: 5010 | B5011: 98.133504
A5012: 5011 | B5012: 99.612669
A5013: 5012 | B5013: 97.348526
... A10001: 10000 | B10001: 97.63997

Sheet Sensitivity
A1: PSA speed (same 10,000 paths)
A2: case | B2: clean value | C2: model − bid | D2: OAS at bid (bp)
A3: 100 PSA | B3: 98.086601 | C3: 0.34831933 | D3: 18.167925
A4: 150 PSA | B4: 98.158609 | C4: 0.42032773 | D4: 22.901145
A5: 178 PSA | B5: 98.197988 | C5: 0.45970715 | D5: 25.669507
A6: 200 PSA | B6: 98.22846 | C6: 0.49017906 | D6: 27.906362
A7: 258 PSA | B7: 98.306849 | C7: 0.56856753 | D7: 34.075495
A8: 300 PSA | B8: 98.361884 | C8: 0.62360236 | D8: 38.801651
A11: Refinancing sensitivity beta
A12: case | B12: clean value | C12: model − bid | D12: OAS at bid (bp) | E12: option cost vs β=0
A13: β = 0.0 | B13: 98.230952 | C13: 0.49267032 | D13: 27.466521 | E13: 0
A14: β = 0.2 | B14: 98.197988 | C14: 0.45970715 | D14: 25.669507 | E14: 0.032963169
A15: β = 0.4 | B15: 98.187554 | C15: 0.44927226 | D15: 25.214582 | E15: 0.043398066
A18: Rate volatility
A19: case | B19: clean value | C19: model − bid | D19: OAS at bid (bp)
A20: σ × 0.5 | B20: 98.221184 | C20: 0.48290257 | D20: 26.926713
A21: σ × 1.0 | B21: 98.197988 | C21: 0.45970715 | D21: 25.669507
A22: σ × 1.5 | B22: 98.169256 | C22: 0.43097471 | D22: 24.130531
A25: Private-label clean value: annual PD (rows) x recovery (columns)
A26: Annual PD | B26: R = 25% | C26: R = 40% | D26: R = 60%
A27: 0.05% | B27: 98.130136 | C27: 98.143899 | D27: 98.16225
A28: 0.10% | B28: 98.062339 | C28: 98.089854 | D28: 98.12654
A29: 0.25% | B29: 97.859283 | C29: 97.927986 | D29: 98.01959
A30: 0.50% | B30: 97.521969 | C30: 97.659094 | D30: 97.841927
A31: 1.00% | B31: 96.851496 | C31: 97.124626 | D31: 97.488801
A32: 2.00% | B32: 95.527039 | C32: 96.068853 | D32: 96.791273
A35: Bridge from the original Excel method to the corrected value
A36: Step | B36: Value per 100
A37: Original method (10y-yield random walk from 4.387%, DF=(1+r_t/12)^-t), 10,000 paths | B37: 97.510763
A38: + path-wise cumulative discount factors ∏(1+r_k/12)^-1 | B38: 97.488443
A39: + short-rate paths calibrated to the Treasury zero curve | B39: 98.419103
A40: + actual payment dates (25th of following month) | B40: 98.472618
A41: − accrued interest (compare clean with clean) | B41: 98.230952
A42: + refinancing overlay β = 0.20 (path-dependent cash flows) = final | B42: 98.197988

Sheet Corrections Log
A1: # | B1: Original model | C1: Correction
A2: 1 | B2: Discount factor DF_t = 1/(1+r_t/12)^t used only the month-t rate as if it were a spot rate. | C2: Path-wise cumulative discount factor: product of 1/(1+r_k/12) over k = 0..t-1.
A3: 2 | B3: Rate paths were a driftless random walk started at the 10-year yield (4.387%), unrelated to the curve. | C3: One-month short-rate paths with drift calibrated so that average discount factors reprice the Treasury zero curve.
A4: 3 | B4: Cash flows were identical on every path (PSA only), so the simulation could not value the prepayment option. | C4: PSA speed responds to the simulated rate change (beta = 0.20, bounded 0.75x-1.75x).
A5: 4 | B5: RAND() with 100 paths: results changed on every recalculation; s.e. about 0.13, so cheap/rich flipped across PSA cases. | C5: 10,000 antithetic paths with a fixed seed; the same paths for every scenario.
A6: 5 | B6: Report quoted three different agency prices (97.5371, 97.4949) and market prices 97.7383 / 97.7393. | C6: Single set of reproducible numbers generated by the notebooks.
A7: 6 | B7: Clean BVAL price compared with the value of cash flows assumed paid at month-end. | C7: Cash flows discounted to the actual 25th-of-month payment dates; accrued interest subtracted before comparing.
A8: 7 | B8: Private-label expected CF = CF_t x (S_t + R x q_t): recovery only on one month's cash flow. | C8: E[CF_t] = S_t x CF_t + q_t x R x B_(t-1): recovery on the outstanding principal claim.
A9: 8 | B9: Private-label price (97.5371) came from a different random draw and was higher than the agency price. | C9: Both parts valued on identical paths; the private-label value is always below the agency value.
A10: 9 | B10: Volatility series included a 5-day change (30 Apr to 5 May 2026). | C10: Month-end changes only, through the 30 Apr 2026 valuation date.
