Workbook

Sheet Inputs
A1: INPUTS — All hardcoded values (blue). Formulas reference these cells.
A2: Blue = hardcoded input | Black = formula | Source: Bloomberg Terminal, 3/20/2026
A4: Treasury Bond | B4: Value | D4: TIPS | E4: Value | G4: Price build-up (per $100) | H4: Value | I4: Note
A5: Full Price P | B5: =H5+H6 -> 96.928436 | D5: Full Price V | E5: =H7+H8 -> 97.675458 | G5: Treasury clean price (96-19+) | H5: =96+19.5/32 -> 96.609375 | I5: Bloomberg ask, quoted in 32nds
A6: Semiannual Coupon c | B6: 1.75 | D6: Semiannual Coupon s | E6: 0.5625 | G6: Treasury accrued (33 of 181 days) | H6: =B6*33/181 -> 0.31906077 | I6: Act/Act: 2/15/2026 to 3/20/2026
A7: Settlement Date | B7: 3/20/2026 | D7: Settlement Date | E7: 3/20/2026 | G7: TIPS clean real price (97-15 1/4) | H7: =97+15.25/32 -> 97.476562 | I7: Bloomberg ask, quoted in 32nds (real, unindexed)
A8: Maturity Date | B8: 2/15/2033 | D8: Maturity Date | E8: 1/15/2033 | G8: TIPS real accrued (64 of 181 days) | H8: =E6*64/181 -> 0.19889503 | I8: Act/Act: 1/15/2026 to 3/20/2026. As submitted: 0.261864 (not consistent with 64 days)
A9: Annual Coupon | B9: 3.500% | D9: Annual Coupon | E9: 1.125%
A11: Period (yrs) | B11: Source quote(s) | C11: Method | D11: Interpolated Rate (%) | G11: Tenor (yrs) | H11: Ticker | I11: Market Rate (%)
A12: 0.5 | B12: USSWIT1 | C12: Flat extrapolation from 1Y | D12: =I12 -> 2.704 | G12: 1 | H12: USSWIT1 | I12: 2.704
A13: 1 | B13: USSWIT1 | C13: Market quote | D13: =I12 -> 2.704 | G13: 2 | H13: USSWIT2 | I13: 2.522
A14: 1.5 | B14: USSWIT1/2 | C14: Linear interp 1Y-2Y | D14: =(I12+I13)/2 -> 2.613 | G14: 3 | H14: USSWIT3 | I14: 2.477
A15: 2 | B15: USSWIT2 | C15: Market quote | D15: =I13 -> 2.522 | G15: 4 | H15: USSWIT4 | I15: 2.451
A16: 2.5 | B16: USSWIT2/3 | C16: Linear interp 2Y-3Y | D16: =(I13+I14)/2 -> 2.4995 | G16: 5 | H16: USSWIT5 | I16: 2.42
A17: 3 | B17: USSWIT3 | C17: Market quote | D17: =I14 -> 2.477 | G17: 6 | H17: USSWIT6 | I17: 2.444
A18: 3.5 | B18: USSWIT3/4 | C18: Linear interp 3Y-4Y | D18: =(I14+I15)/2 -> 2.464 | G18: 7 | H18: USSWIT7 | I18: 2.425
A19: 4 | B19: USSWIT4 | C19: Market quote | D19: =I15 -> 2.451
A20: 4.5 | B20: USSWIT4/5 | C20: Linear interp 4Y-5Y | D20: =(I15+I16)/2 -> 2.4355
A21: 5 | B21: USSWIT5 | C21: Market quote | D21: =I16 -> 2.42
A22: 5.5 | B22: USSWIT5/6 | C22: Linear interp 5Y-6Y | D22: =(I16+I17)/2 -> 2.432
A23: 6 | B23: USSWIT6 | C23: Market quote | D23: =I17 -> 2.444
A24: 6.5 | B24: USSWIT6/7 | C24: Linear interp 6Y-7Y | D24: =(I17+I18)/2 -> 2.4345
A25: 7 | B25: USSWIT7 | C25: Market quote | D25: =I18 -> 2.425
A28: Period # | B28: Coupon Date | C28: STRIPS Price D(t) | D28: Years t
A29: 1 | B29: 8/15/2026 | C29: 98.515 | D29: 0.405202
A30: 2 | B30: 2/15/2027 | C30: 96.8006 | D30: 0.908966
A31: 3 | B31: 8/15/2027 | C31: 94.882 | D31: 1.404517
A32: 4 | B32: 2/15/2028 | C32: 93.0997 | D32: 1.908282
A33: 5 | B33: 8/15/2028 | C33: 91.3442 | D33: 2.406571
A34: 6 | B34: 2/15/2029 | C34: 89.613 | D34: 2.910335
A35: 7 | B35: 8/15/2029 | C35: 87.8689 | D35: 3.405886
A36: 8 | B36: 2/15/2030 | C36: 86.122 | D36: 3.909651
A37: 9 | B37: 8/15/2030 | C37: 84.3968 | D37: 4.405202
A38: 10 | B38: 2/15/2031 | C38: 82.6731 | D38: 4.908966
A39: 11 | B39: 8/15/2031 | C39: 80.9573 | D39: 5.404517
A40: 12 | B40: 2/15/2032 | C40: 79.1574 | D40: 5.908282
... A42: 14 | B42: 2/15/2033 | C42: 75.6917 | D42: 6.910335

Sheet Calculations
A1: CALCULATIONS — All values driven by formulas referencing Inputs sheet
A2: Black = formula | Double-click any cell to see the formula | All references → Inputs sheet
A4: # | B4: Date | C4: Years t | D4: Swap Rate f_t (%) | E4: F_t=(1+f_t)^t | F4: x_t (STRIPS notional) | G4: D(t) (STRIPS price) | H4: STRIPS Cost x_t×D(t)/100
A5: =Inputs!A29 -> 1 | B5: =Inputs!B29 -> 8/15/2026 | C5: =Inputs!D29 -> 0.405202 | D5: =Inputs!D12 -> 2.704 | E5: =(1+D5/100)^C5 -> 1.0108698 | F5: =Inputs!$B$6 - Inputs!$E$6*E5 -> 1.1813857 | G5: =Inputs!C29 -> 98.515 | H5: =F5*G5/100 -> 1.1638422
A6: =Inputs!A30 -> 2 | B6: =Inputs!B30 -> 2/15/2027 | C6: =Inputs!D30 -> 0.908966 | D6: =Inputs!D13 -> 2.704 | E6: =(1+D6/100)^C6 -> 1.0245485 | F6: =Inputs!$B$6 - Inputs!$E$6*E6 -> 1.1736915 | G6: =Inputs!C30 -> 96.8006 | H6: =F6*G6/100 -> 1.1361404
A7: =Inputs!A31 -> 3 | B7: =Inputs!B31 -> 8/15/2027 | C7: =Inputs!D31 -> 1.404517 | D7: =Inputs!D14 -> 2.613 | E7: =(1+D7/100)^C7 -> 1.036893 | F7: =Inputs!$B$6 - Inputs!$E$6*E7 -> 1.1667477 | G7: =Inputs!C31 -> 94.882 | H7: =F7*G7/100 -> 1.1070335
A8: =Inputs!A32 -> 4 | B8: =Inputs!B32 -> 2/15/2028 | C8: =Inputs!D32 -> 1.908282 | D8: =Inputs!D15 -> 2.522 | E8: =(1+D8/100)^C8 -> 1.0486777 | F8: =Inputs!$B$6 - Inputs!$E$6*E8 -> 1.1601188 | G8: =Inputs!C32 -> 93.0997 | H8: =F8*G8/100 -> 1.0800671
A9: =Inputs!A33 -> 5 | B9: =Inputs!B33 -> 8/15/2028 | C9: =Inputs!D33 -> 2.406571 | D9: =Inputs!D16 -> 2.4995 | E9: =(1+D9/100)^C9 -> 1.0612132 | F9: =Inputs!$B$6 - Inputs!$E$6*E9 -> 1.1530676 | G9: =Inputs!C33 -> 91.3442 | H9: =F9*G9/100 -> 1.0532603
A10: =Inputs!A34 -> 6 | B10: =Inputs!B34 -> 2/15/2029 | C10: =Inputs!D34 -> 2.910335 | D10: =Inputs!D17 -> 2.477 | E10: =(1+D10/100)^C10 -> 1.0738074 | F10: =Inputs!$B$6 - Inputs!$E$6*E10 -> 1.1459833 | G10: =Inputs!C34 -> 89.613 | H10: =F10*G10/100 -> 1.02695
A11: =Inputs!A35 -> 7 | B11: =Inputs!B35 -> 8/15/2029 | C11: =Inputs!D35 -> 3.405886 | D11: =Inputs!D18 -> 2.464 | E11: =(1+D11/100)^C11 -> 1.0864373 | F11: =Inputs!$B$6 - Inputs!$E$6*E11 -> 1.138879 | G11: =Inputs!C35 -> 87.8689 | H11: =F11*G11/100 -> 1.0007205
A12: =Inputs!A36 -> 8 | B12: =Inputs!B36 -> 2/15/2030 | C12: =Inputs!D36 -> 3.909651 | D12: =Inputs!D19 -> 2.451 | E12: =(1+D12/100)^C12 -> 1.0992961 | F12: =Inputs!$B$6 - Inputs!$E$6*E12 -> 1.131646 | G12: =Inputs!C36 -> 86.122 | H12: =F12*G12/100 -> 0.97459613
A13: =Inputs!A37 -> 9 | B13: =Inputs!B37 -> 8/15/2030 | C13: =Inputs!D37 -> 4.405202 | D13: =Inputs!D20 -> 2.4355 | E13: =(1+D13/100)^C13 -> 1.1118252 | F13: =Inputs!$B$6 - Inputs!$E$6*E13 -> 1.1245983 | G13: =Inputs!C37 -> 84.3968 | H13: =F13*G13/100 -> 0.94912498
A14: =Inputs!A38 -> 10 | B14: =Inputs!B38 -> 2/15/2031 | C14: =Inputs!D38 -> 4.908966 | D14: =Inputs!D21 -> 2.42 | E14: =(1+D14/100)^C14 -> 1.1245493 | F14: =Inputs!$B$6 - Inputs!$E$6*E14 -> 1.117441 | G14: =Inputs!C38 -> 82.6731 | H14: =F14*G14/100 -> 0.92382314
A15: =Inputs!A39 -> 11 | B15: =Inputs!B39 -> 8/15/2031 | C15: =Inputs!D39 -> 5.404517 | D15: =Inputs!D22 -> 2.432 | E15: =(1+D15/100)^C15 -> 1.1386747 | F15: =Inputs!$B$6 - Inputs!$E$6*E15 -> 1.1094955 | G15: =Inputs!C39 -> 80.9573 | H15: =F15*G15/100 -> 0.8982176
A16: =Inputs!A40 -> 12 | B16: =Inputs!B40 -> 2/15/2032 | C16: =Inputs!D40 -> 5.908282 | D16: =Inputs!D23 -> 2.444 | E16: =(1+D16/100)^C16 -> 1.15334 | F16: =Inputs!$B$6 - Inputs!$E$6*E16 -> 1.1012462 | G16: =Inputs!C40 -> 79.1574 | H16: =F16*G16/100 -> 0.87171789
A17: =Inputs!A41 -> 13 | B17: =Inputs!B41 -> 8/15/2032 | C17: =Inputs!D41 -> 6.406571 | D17: =Inputs!D24 -> 2.4345 | E17: =(1+D17/100)^C17 -> 1.1666072 | F17: =Inputs!$B$6 - Inputs!$E$6*E17 -> 1.0937834 | G17: =Inputs!C41 -> 77.4806 | H17: =F17*G17/100 -> 0.84746998
A18: =Inputs!A42 -> 14 | B18: =Inputs!B42 -> 2/15/2033 | C18: =Inputs!D42 -> 6.910335 | D18: =Inputs!D25 -> 2.425 | E18: =(1+D18/100)^C18 -> 1.1800727 | F18: =(Inputs!$B$6+100) - (Inputs!$E$6+100)*E18 -> -16.921059 | G18: =Inputs!C42 -> 75.6917 | H18: =F18*G18/100 -> -12.807837
A19: TOTAL | H19: =SUM(H5:H18) -> 0.22512654

Sheet Table II
A1: Table II — Synthetic Treasury Bond Replicating Strategy | T 3.500 2/15/2033 vs TII 1.125 1/15/2033
A2: Settlement: 3/20/2026 | All cash flows per $100 notional | Iₜ = inflation index ratio (variable — cancels in Total column)
A4: Date | B4: Treasury Cash Flow | C4: TIPS Cash Flow | D4: Inflation Swap Cash Flow | E4: STRIPS Cash Flow | F4: STRIPS Price D(t) | G4: Total Cash Flow
A5: 0 | B5: =-Inputs!B5 -> -96.928436 | C5: =-Inputs!E5 -> -97.675458 | D5: 0 | E5: =-Calculations!H19 -> -0.22512654 | F5: — | G5: =C5+D5+E5 -> -97.900584
A6: =Calculations!B5 -> 8/15/2026 | B6: =Inputs!$B$6 -> 1.75 | C6: =TEXT(Inputs!$E$6,"0.0000")&"·I1" -> 0.5625·I1 | D6: =TEXT(Inputs!$E$6,"0.0000")&"·(F1−I1)" -> 0.5625·(F1−I1) | E6: =Calculations!F5 -> 1.1813857 | F6: =Calculations!G5 -> 98.515 | G6: =Inputs!$B$6 -> 1.75
A7: =Calculations!B6 -> 2/15/2027 | B7: =Inputs!$B$6 -> 1.75 | C7: =TEXT(Inputs!$E$6,"0.0000")&"·I2" -> 0.5625·I2 | D7: =TEXT(Inputs!$E$6,"0.0000")&"·(F2−I2)" -> 0.5625·(F2−I2) | E7: =Calculations!F6 -> 1.1736915 | F7: =Calculations!G6 -> 96.8006 | G7: =Inputs!$B$6 -> 1.75
A8: =Calculations!B7 -> 8/15/2027 | B8: =Inputs!$B$6 -> 1.75 | C8: =TEXT(Inputs!$E$6,"0.0000")&"·I3" -> 0.5625·I3 | D8: =TEXT(Inputs!$E$6,"0.0000")&"·(F3−I3)" -> 0.5625·(F3−I3) | E8: =Calculations!F7 -> 1.1667477 | F8: =Calculations!G7 -> 94.882 | G8: =Inputs!$B$6 -> 1.75
A9: =Calculations!B8 -> 2/15/2028 | B9: =Inputs!$B$6 -> 1.75 | C9: =TEXT(Inputs!$E$6,"0.0000")&"·I4" -> 0.5625·I4 | D9: =TEXT(Inputs!$E$6,"0.0000")&"·(F4−I4)" -> 0.5625·(F4−I4) | E9: =Calculations!F8 -> 1.1601188 | F9: =Calculations!G8 -> 93.0997 | G9: =Inputs!$B$6 -> 1.75
A10: =Calculations!B9 -> 8/15/2028 | B10: =Inputs!$B$6 -> 1.75 | C10: =TEXT(Inputs!$E$6,"0.0000")&"·I5" -> 0.5625·I5 | D10: =TEXT(Inputs!$E$6,"0.0000")&"·(F5−I5)" -> 0.5625·(F5−I5) | E10: =Calculations!F9 -> 1.1530676 | F10: =Calculations!G9 -> 91.3442 | G10: =Inputs!$B$6 -> 1.75
A11: =Calculations!B10 -> 2/15/2029 | B11: =Inputs!$B$6 -> 1.75 | C11: =TEXT(Inputs!$E$6,"0.0000")&"·I6" -> 0.5625·I6 | D11: =TEXT(Inputs!$E$6,"0.0000")&"·(F6−I6)" -> 0.5625·(F6−I6) | E11: =Calculations!F10 -> 1.1459833 | F11: =Calculations!G10 -> 89.613 | G11: =Inputs!$B$6 -> 1.75
A12: =Calculations!B11 -> 8/15/2029 | B12: =Inputs!$B$6 -> 1.75 | C12: =TEXT(Inputs!$E$6,"0.0000")&"·I7" -> 0.5625·I7 | D12: =TEXT(Inputs!$E$6,"0.0000")&"·(F7−I7)" -> 0.5625·(F7−I7) | E12: =Calculations!F11 -> 1.138879 | F12: =Calculations!G11 -> 87.8689 | G12: =Inputs!$B$6 -> 1.75
A13: =Calculations!B12 -> 2/15/2030 | B13: =Inputs!$B$6 -> 1.75 | C13: =TEXT(Inputs!$E$6,"0.0000")&"·I8" -> 0.5625·I8 | D13: =TEXT(Inputs!$E$6,"0.0000")&"·(F8−I8)" -> 0.5625·(F8−I8) | E13: =Calculations!F12 -> 1.131646 | F13: =Calculations!G12 -> 86.122 | G13: =Inputs!$B$6 -> 1.75
A14: =Calculations!B13 -> 8/15/2030 | B14: =Inputs!$B$6 -> 1.75 | C14: =TEXT(Inputs!$E$6,"0.0000")&"·I9" -> 0.5625·I9 | D14: =TEXT(Inputs!$E$6,"0.0000")&"·(F9−I9)" -> 0.5625·(F9−I9) | E14: =Calculations!F13 -> 1.1245983 | F14: =Calculations!G13 -> 84.3968 | G14: =Inputs!$B$6 -> 1.75
A15: =Calculations!B14 -> 2/15/2031 | B15: =Inputs!$B$6 -> 1.75 | C15: =TEXT(Inputs!$E$6,"0.0000")&"·I10" -> 0.5625·I10 | D15: =TEXT(Inputs!$E$6,"0.0000")&"·(F10−I10)" -> 0.5625·(F10−I10) | E15: =Calculations!F14 -> 1.117441 | F15: =Calculations!G14 -> 82.6731 | G15: =Inputs!$B$6 -> 1.75
A16: =Calculations!B15 -> 8/15/2031 | B16: =Inputs!$B$6 -> 1.75 | C16: =TEXT(Inputs!$E$6,"0.0000")&"·I11" -> 0.5625·I11 | D16: =TEXT(Inputs!$E$6,"0.0000")&"·(F11−I11)" -> 0.5625·(F11−I11) | E16: =Calculations!F15 -> 1.1094955 | F16: =Calculations!G15 -> 80.9573 | G16: =Inputs!$B$6 -> 1.75
A17: =Calculations!B16 -> 2/15/2032 | B17: =Inputs!$B$6 -> 1.75 | C17: =TEXT(Inputs!$E$6,"0.0000")&"·I12" -> 0.5625·I12 | D17: =TEXT(Inputs!$E$6,"0.0000")&"·(F12−I12)" -> 0.5625·(F12−I12) | E17: =Calculations!F16 -> 1.1012462 | F17: =Calculations!G16 -> 79.1574 | G17: =Inputs!$B$6 -> 1.75
A18: =Calculations!B17 -> 8/15/2032 | B18: =Inputs!$B$6 -> 1.75 | C18: =TEXT(Inputs!$E$6,"0.0000")&"·I13" -> 0.5625·I13 | D18: =TEXT(Inputs!$E$6,"0.0000")&"·(F13−I13)" -> 0.5625·(F13−I13) | E18: =Calculations!F17 -> 1.0937834 | F18: =Calculations!G17 -> 77.4806 | G18: =Inputs!$B$6 -> 1.75
A19: =Calculations!B18 -> 2/15/2033 | B19: =Inputs!$B$6+100 -> 101.75 | C19: =TEXT(Inputs!$E$6+100,"0.0000")&"·I14" -> 100.5625·I14 | D19: =TEXT(Inputs!$E$6+100,"0.0000")&"·(F14−I14)" -> 100.5625·(F14−I14) | E19: =Calculations!F18 -> -16.921059 | F19: =Calculations!G18 -> 75.6917 | G19: =Inputs!$B$6+100 -> 101.75

Sheet Mispricing
A1: Mispricing Summary
A3: Item | B3: Value (per $100) | C3: Formula / Note
A4: Treasury Bond Full Price (P) | B4: =Inputs!B5 -> 96.928436 | C4: Clean price + accrued (Inputs!G5:H6)
A5: TIPS Full Price (V) | B5: =Inputs!E5 -> 97.675458 | C5: Real clean price + real accrued (Inputs!G7:H8)
A6: Total STRIPS Cost Σ xₜ·D(t)/100 | B6: =Calculations!H19 -> 0.22512654 | C6: SUM of all 14 STRIPS positions x price/100
A7: Synthetic Price = V + STRIPS Cost | B7: =Inputs!E5 + Calculations!H19 -> 97.900584 | C7: Cost of replicating portfolio
A8: Mispricing = P − Synthetic | B8: =Inputs!B5 - (Inputs!E5 + Calculations!H19) -> -0.97214829 | C8: Positive → Treasury expensive; Negative → TIPS expensive
A9: Interpretation | B9: =IF(B8<0,"TIPS relatively expensive (Treasury cheap)","Treasury relatively expensive (TIPS cheap)") -> TIPS relatively expensive (Treasury cheap) | C9: Consistent with post-2009 narrowing of TIPS-Treasury arbitrage
A11: What the Mispricing Means
A12: A negative mispricing means the synthetic replicating portfolio (TIPS + inflation swaps + STRIPS) costs MORE than the actual Treasury bond, i.e. TIPS are relatively expensive compared to nominal Treasuries. This is the opposite sign to Fleckenstein, Longstaff and Lustig (2004-2009 sample), and the roughly $0.97 gap is far smaller than the $23.10 in the paper's Table II example (December 30, 2008).

Sheet Corrections
A1: Location | B1: As submitted | C1: Corrected | D1: Reason
A2: Table II!G5 | B2: Formula B5+C5+D5+E5 (-194.89) | C2: Formula C5+D5+E5 (-97.90) | D2: Date-0 total of the replicating portfolio must exclude the Treasury leg it replicates (as in the paper's Table II).
A3: Mispricing!B9 | B3: IF(B7<0,...) -> 'Treasury relatively expensive' | C3: IF(B8<0,...) -> 'TIPS relatively expensive' | D3: Test referenced the synthetic price (always positive) instead of the mispricing.
A4: Inputs!E5 (TIPS full price V) | B4: 97.738427 (accrued 0.261864) | C4: H7+H8 = 97.675458 (accrued 0.198895) | D4: Real accrued on 1.125% TIPS for 64 of 181 days is 0.5625*64/181 = 0.198895; the submitted figure is not consistent with the stated 64 days.
A5: Inputs!B5 (Treasury full price P) | B5: 96.928436 (hardcoded) | C5: H5+H6 = 96.928436 | D5: Made formula-driven; value unchanged (33 of 181 days accrued).
A6: Inputs!A11:I25 | B6: Tickers/rates mislabelled (e.g. 1.0y row showed USSWIT2 2.522; rates under 'Period (yrs)' header) | C6: Quotes moved to G11:I18; grid relabelled | D6: Labelling only; interpolated rates unchanged.
